llmprint/__init__.py
llmprint/main.py
llmprint-0.1.2.dist-info/LICENSE
llmprint-0.1.2.dist-info/METADATA
llmprint-0.1.2.dist-info/WHEEL
llmprint-0.1.2.dist-info/entry_points.txt
llmprint-0.1.2.dist-info/top_level.txt
llmprint-0.1.2.dist-info/RECORD
