Metadata-Version: 2.1
Name: llmprint
Version: 0.1.2
Summary: CLI tool to print directory structure and file contents for LLM context generation
Home-page: https://github.com/rsh3khar/llmprint
Author: Raj Shekhar
Project-URL: Homepage, https://github.com/rsh3khar/llmprint
Project-URL: Bug Tracker, https://github.com/rsh3khar/llmprint/issues
Keywords: llm ai chatgpt claude directory-tree file-contents clipboard utility development tool
Classifier: Development Status :: 4 - Beta
Classifier: Environment :: Console
Classifier: Intended Audience :: Developers
Classifier: Intended Audience :: Science/Research
Classifier: Topic :: Software Development :: Libraries :: Python Modules
Classifier: Topic :: Utilities
Classifier: Topic :: Text Processing :: General
Classifier: Topic :: Scientific/Engineering :: Artificial Intelligence
Classifier: Programming Language :: Python :: 3
Classifier: Programming Language :: Python :: 3.6
Classifier: Programming Language :: Python :: 3.7
Classifier: Programming Language :: Python :: 3.8
Classifier: Programming Language :: Python :: 3.9
Classifier: Programming Language :: Python :: 3.10
Classifier: Programming Language :: Python :: 3.11
Classifier: Programming Language :: Python :: 3.12
Classifier: License :: OSI Approved :: MIT License
Classifier: Operating System :: OS Independent
Requires-Python: >=3.6
License-File: LICENSE
Requires-Dist: pyperclip>=1.8.0
